smartem_epuplayer/__init__.py
smartem_epuplayer/__main__.py
smartem_epuplayer/cli.py
smartem_epuplayer/models.py
smartem_epuplayer/recorder.py
smartem_epuplayer/replayer.py
smartem_epuplayer-1.1.0.dist-info/METADATA
smartem_epuplayer-1.1.0.dist-info/WHEEL
smartem_epuplayer-1.1.0.dist-info/entry_points.txt
smartem_epuplayer-1.1.0.dist-info/RECORD
