Metadata-Version: 2.4
Name: smartem-epuplayer
Version: 1.1.0
Summary: Filesystem Recording and Replay Tool for cryo-EM development and testing
Project-URL: Homepage, https://github.com/DiamondLightSource/smartem-devtools
Project-URL: Repository, https://github.com/DiamondLightSource/smartem-devtools
Project-URL: Documentation, https://github.com/DiamondLightSource/smartem-devtools#epuplayer
Project-URL: Issues, https://github.com/DiamondLightSource/smartem-devtools/issues
Author-email: Diamond Light Source <smartem@diamond.ac.uk>
License-Expression: Apache-2.0
Keywords: cryo-em,filesystem,recording,replay,smartem,testing
Classifier: Development Status :: 5 - Production/Stable
Classifier: Environment :: Console
Classifier: Intended Audience :: Developers
Classifier: Intended Audience :: Science/Research
Classifier: License :: OSI Approved :: Apache Software License
Classifier: Operating System :: OS Independent
Classifier: Programming Language :: Python :: 3
Classifier: Programming Language :: Python :: 3.12
Classifier: Programming Language :: Python :: 3.13
Classifier: Topic :: Software Development :: Testing
Classifier: Topic :: System :: Filesystems
Classifier: Typing :: Typed
Requires-Python: >=3.12
Requires-Dist: watchdog<7.0.0,>=4.0.0
Provides-Extra: dev
Requires-Dist: pytest>=8.0.0; extra == 'dev'
Requires-Dist: ruff>=0.8.0; extra == 'dev'
